whakaari/__init__.py
whakaari/forecast_model.py
whakaari/tremor_data.py
whakaari/utils.py
whakaari-0.0.1.dist-info/METADATA
whakaari-0.0.1.dist-info/WHEEL
whakaari-0.0.1.dist-info/licenses/LICENSE
whakaari-0.0.1.dist-info/RECORD
