Metadata-Version: 2.1
Name: whakaari
Version: 0.0.1
Summary: Whakaari Forecast Modelling
Project-URL: Homepage, https://github.com/martanto/whakaari
Project-URL: Issues, https://github.com/martanto/whakaari/issues
Author-email: David Dempsey <d.dempsey@auckland.ac.nz>
Maintainer-email: Martanto <martanto@live.com>
License: MIT License
License-File: LICENSE
Keywords: forecast,modelling,volcano,volcanoes,whakaari
Classifier: License :: OSI Approved :: MIT License
Classifier: Operating System :: OS Independent
Classifier: Programming Language :: Python :: 3.7
Requires-Python: >=3.7.6
Requires-Dist: corner==2.0.1
Requires-Dist: imbalanced-learn==0.6.1
Requires-Dist: joblib==0.14.0
Requires-Dist: numpy==1.18.1
Requires-Dist: obspy==1.1.0
Requires-Dist: openpyxl==3.1.3
Requires-Dist: pandas==0.25.3
Requires-Dist: scikit-learn==0.22
Requires-Dist: scipy==1.3.1
Requires-Dist: statsmodels==0.10.2
Requires-Dist: tsfresh==0.16.0
